[
    {
        "title":"Alice no País das Maravilhas",
        "image":"AliceWonderland",
        "audioName":"bensound-lofinerdbassbuzzer"
    },
    {
        "title":"A Bela adormecida",
        "image":"SleepingBeauty",
        "audioName":"bensound-lofinerdbassbuzzer"
    },
    {
        "title":"O patinho feio",
        "image":"Duckling",
        "audioName":"bensound-lofinerdbassbuzzer"
    },
    {
        "title":"Pinóquio",
        "image":"Pinocchio",
        "audioName":"bensound-lofinerdbassbuzzer"
    }
]
